UO/test_functions/CUTE.py
UO/test_functions/DIXMAAN.py
UO/test_functions/__init__.py
UO/test_functions/diagonal_functions.py
UO/test_functions/exceptions.py
UO/test_functions/full_hessian_functions.py
UO/test_functions/functions.py
UO/test_functions/quadratic_functions.py
UO/test_functions/support_funcs.py
UO/test_functions/test_function.py
UO/test_functions/test_functions_factory.py
UO/test_functions/test_functions_register.py
UO_test_functions-1.0.3.dist-info/DESCRIPTION.rst
UO_test_functions-1.0.3.dist-info/METADATA
UO_test_functions-1.0.3.dist-info/RECORD
UO_test_functions-1.0.3.dist-info/WHEEL
UO_test_functions-1.0.3.dist-info/metadata.json
UO_test_functions-1.0.3.dist-info/top_level.txt
