Metadata-Version: 2.0
Name: UO-test-functions
Version: 1.0.3
Summary: An Unconstrained Optimization Test Functions Collection
Home-page: https://github.com/SupremaLex/UO-test-funcs/
Author: George Lutsenko
Author-email: georglutsenko@gmail.com
License: UNKNOWN
Project-URL: Bug Reports, https://github.com/SupremaLex/UO-test-funcs/issues
Project-URL: Source, https://github.com/SupremaLex/UO-test-funcs/
Keywords: minimization unconstrained-optimization test-functions optimization
Platform: UNKNOWN
Classifier: Development Status :: 3 - Alpha
Classifier: Intended Audience :: Science/Research
Classifier: Intended Audience :: Education
Classifier: Topic :: Scientific/Engineering :: Mathematics
Classifier: License :: OSI Approved :: MIT License
Classifier: Programming Language :: Python :: 3.5
Classifier: Programming Language :: Python :: 3.6
Requires-Dist: matplotlib
Requires-Dist: numpy
Requires-Dist: sympy
